.gitignore
CHANGES.txt
LICENSE
MANIFEST.in
README.rst
setup.py
src/objgraph_middleware/__init__.py
src/objgraph_middleware.egg-info/PKG-INFO
src/objgraph_middleware.egg-info/SOURCES.txt
src/objgraph_middleware.egg-info/dependency_links.txt
src/objgraph_middleware.egg-info/requires.txt
src/objgraph_middleware.egg-info/top_level.txt
src/objgraph_middleware.egg-info/zip-safe
src/objgraph_middleware/tests/__init__.py
src/objgraph_middleware/tests/test_middleware.py