Metadata-Version: 1.0
Name: objgraph-middleware
Version: 0.2
Summary: Memory data logging middleware
Home-page: UNKNOWN
Author: Ignas Mikalajunas
Author-email: ignas@uber.com
License: MIT
Keywords: web wsgi flask middleware objgraph memory profiling
Platform: UNKNOWN
Classifier: Programming Language :: Python
Classifier: Topic :: Internet :: WWW/HTTP
Classifier: Topic :: Internet :: WWW/HTTP :: WSGI :: Middleware
